[
  {
    "model": "api.interesse",
    "pk": 1,
    "fields": {
      "id_leggo": "051f84b38db85f0e236aa04140c7dc87",
      "interesse": "direitos-humanos",
      "apelido": "Legítima defesa invasão de propriedade",
      "tema": "Direito Penal;Legítima defesa;Propriedade",
      "tema_slug": "direito-penal;legitima-defesa;propriedade",
      "keywords": "nan",
      "advocacy_link": "nan",
      "tipo_agenda": "nan",
      "proposicao": 1,
      "nome_interesse": "Direitos Humanos",
      "descricao_interesse": "."
    }
  },
  {
    "model": "api.interesse",
    "pk": 2,
    "fields": {
      "id_leggo": "0b824ee5751e80e1be660173a406642c",
      "interesse": "direitos-humanos",
      "apelido": "Sistema Nacional de Educação (SNE)",
      "tema": "Educação",
      "tema_slug": "educacao",
      "keywords": "nan",
      "advocacy_link": "nan",
      "tipo_agenda": "nan",
      "proposicao": 2,
      "nome_interesse": "Direitos Humanos",
      "descricao_interesse": "."
    }
  },
  {
    "model": "api.interesse",
    "pk": 3,
    "fields": {
      "id_leggo": "165ac872ecfb7335b752eee135f76da8",
      "interesse": "direitos-humanos",
      "apelido": "nan",
      "tema": "nan",
      "tema_slug": "nan",
      "keywords": "nan",
      "advocacy_link": "nan",
      "tipo_agenda": "nan",
      "proposicao": 3,
      "nome_interesse": "Direitos Humanos",
      "descricao_interesse": "."
    }
  },
  {
    "model": "api.interesse",
    "pk": 4,
    "fields": {
      "id_leggo": "1732b0b9c1dda56feb98bd12eafd0424",
      "interesse": "direitos-humanos",
      "apelido": "PEC Antiaborto",
      "tema": "Gênero;Aborto;Direitos sexuais e reprodutivos",
      "tema_slug": "genero;aborto;direitos-sexuais-e-reprodutivos",
      "keywords": "nan",
      "advocacy_link": "nan",
      "tipo_agenda": "nan",
      "proposicao": 4,
      "nome_interesse": "Direitos Humanos",
      "descricao_interesse": "."
    }
  },
  {
    "model": "api.interesse",
    "pk": 5,
    "fields": {
      "id_leggo": "2b2475eac4b0bd50f918639f5bf416af",
      "interesse": "direitos-humanos",
      "apelido": "Licenciamento compulsório de medicamentos",
      "tema": "Licenciamento compulsório;Medicamentos;Vacinas",
      "tema_slug": "licenciamento-compulsorio;medicamentos;vacinas",
      "keywords": "nan",
      "advocacy_link": "nan",
      "tipo_agenda": "nan",
      "proposicao": 5,
      "nome_interesse": "Direitos Humanos",
      "descricao_interesse": "."
    }
  },
  {
    "model": "api.interesse",
    "pk": 6,
    "fields": {
      "id_leggo": "2d374a10f711f0d71b9efe66c456c6eb",
      "interesse": "direitos-humanos",
      "apelido": "Aumento do tempo de internação",
      "tema": "Segurança pública;Socioeducativo;ECA",
      "tema_slug": "seguranca-publica;socioeducativo;eca",
      "keywords": "nan",
      "advocacy_link": "nan",
      "tipo_agenda": "nan",
      "proposicao": 6,
      "nome_interesse": "Direitos Humanos",
      "descricao_interesse": "."
    }
  },
  {
    "model": "api.interesse",
    "pk": 7,
    "fields": {
      "id_leggo": "2ee550b3bcb3e794a5721059ba985ceb",
      "interesse": "direitos-humanos",
      "apelido": "PL do Veneno",
      "tema": "Meio Ambiente",
      "tema_slug": "meio-ambiente",
      "keywords": "nan",
      "advocacy_link": "nan",
      "tipo_agenda": "nan",
      "proposicao": 7,
      "nome_interesse": "Direitos Humanos",
      "descricao_interesse": "."
    }
  },
  {
    "model": "api.interesse",
    "pk": 8,
    "fields": {
      "id_leggo": "3bfe7405e2bed431df963b9ea42a1adc",
      "interesse": "direitos-humanos",
      "apelido": "Trabalho escravo",
      "tema": "Trabalho escravo",
      "tema_slug": "trabalho-escravo",
      "keywords": "nan",
      "advocacy_link": "nan",
      "tipo_agenda": "nan",
      "proposicao": 8,
      "nome_interesse": "Direitos Humanos",
      "descricao_interesse": "."
    }
  },
  {
    "model": "api.interesse",
    "pk": 9,
    "fields": {
      "id_leggo": "3ec661e7c1211c1ef558ebff11ba8655",
      "interesse": "direitos-humanos",
      "apelido": "Aumento do tempo de internação",
      "tema": "Segurança pública;Socioeducativo;ECA",
      "tema_slug": "seguranca-publica;socioeducativo;eca",
      "keywords": "nan",
      "advocacy_link": "nan",
      "tipo_agenda": "nan",
      "proposicao": 9,
      "nome_interesse": "Direitos Humanos",
      "descricao_interesse": "."
    }
  },
  {
    "model": "api.interesse",
    "pk": 10,
    "fields": {
      "id_leggo": "43bae3f8c01c6a7f9c6fac09befc3041",
      "interesse": "direitos-humanos",
      "apelido": "Trabalho infantil artístico e desportivo",
      "tema": "Trabalho infantil",
      "tema_slug": "trabalho-infantil",
      "keywords": "nan",
      "advocacy_link": "nan",
      "tipo_agenda": "nan",
      "proposicao": 10,
      "nome_interesse": "Direitos Humanos",
      "descricao_interesse": "."
    }
  },
  {
    "model": "api.interesse",
    "pk": 11,
    "fields": {
      "id_leggo": "4a7e4e88fc6143de762f9c9e617b2b80",
      "interesse": "direitos-humanos",
      "apelido": "Excludente de ilicitude",
      "tema": "Segurança pública;Excludente de ilicitude;GLO",
      "tema_slug": "seguranca-publica;excludente-de-ilicitude;glo",
      "keywords": "nan",
      "advocacy_link": "nan",
      "tipo_agenda": "nan",
      "proposicao": 11,
      "nome_interesse": "Direitos Humanos",
      "descricao_interesse": "."
    }
  },
  {
    "model": "api.interesse",
    "pk": 12,
    "fields": {
      "id_leggo": "4e74b87066ee56cbba31cfb537e4cb16",
      "interesse": "direitos-humanos",
      "apelido": "Retorno às aulas na pandemia",
      "tema": "Educação;Pandemia",
      "tema_slug": "educacao;pandemia",
      "keywords": "nan",
      "advocacy_link": "nan",
      "tipo_agenda": "nan",
      "proposicao": 12,
      "nome_interesse": "Direitos Humanos",
      "descricao_interesse": "."
    }
  },
  {
    "model": "api.interesse",
    "pk": 13,
    "fields": {
      "id_leggo": "5101b1662e264b10d270a9811970e995",
      "interesse": "direitos-humanos",
      "apelido": "Licenciamento compulsório de medicamentos",
      "tema": "Licenciamento compulsório;Medicamentos;Vacinas",
      "tema_slug": "licenciamento-compulsorio;medicamentos;vacinas",
      "keywords": "nan",
      "advocacy_link": "nan",
      "tipo_agenda": "nan",
      "proposicao": 13,
      "nome_interesse": "Direitos Humanos",
      "descricao_interesse": "."
    }
  },
  {
    "model": "api.interesse",
    "pk": 14,
    "fields": {
      "id_leggo": "554bb22bbf2e508ce083115fa3621486",
      "interesse": "direitos-humanos",
      "apelido": "nan",
      "tema": "Economia;Finanças Públicas e Orçamento;Saúde",
      "tema_slug": "economia;financas-publicas-e-orcamento;saude",
      "keywords": "nan",
      "advocacy_link": "nan",
      "tipo_agenda": "nan",
      "proposicao": 14,
      "nome_interesse": "Direitos Humanos",
      "descricao_interesse": "."
    }
  },
  {
    "model": "api.interesse",
    "pk": 15,
    "fields": {
      "id_leggo": "66544172d1f060359b4b1f0cc1969a3a",
      "interesse": "direitos-humanos",
      "apelido": "Ensino domiciliar",
      "tema": "Educação;Ensino domiciliar",
      "tema_slug": "educacao;ensino-domiciliar",
      "keywords": "nan",
      "advocacy_link": "nan",
      "tipo_agenda": "nan",
      "proposicao": 15,
      "nome_interesse": "Direitos Humanos",
      "descricao_interesse": "."
    }
  },
  {
    "model": "api.interesse",
    "pk": 16,
    "fields": {
      "id_leggo": "66ccf888166e100ecdae6dc15b5b4ab6",
      "interesse": "direitos-humanos",
      "apelido": "PL do fim dos \"autos de resistência\"",
      "tema": "Direito Penal;Violência policial;Segurança pública",
      "tema_slug": "direito-penal;violencia-policial;seguranca-publica",
      "keywords": "nan",
      "advocacy_link": "nan",
      "tipo_agenda": "nan",
      "proposicao": 16,
      "nome_interesse": "Direitos Humanos",
      "descricao_interesse": "."
    }
  },
  {
    "model": "api.interesse",
    "pk": 17,
    "fields": {
      "id_leggo": "70273486ab6f0eef25ca493b5bc6f2bc",
      "interesse": "direitos-humanos",
      "apelido": "Armamento",
      "tema": "Armamento;Segurança pública",
      "tema_slug": "armamento;seguranca-publica",
      "keywords": "nan",
      "advocacy_link": "nan",
      "tipo_agenda": "nan",
      "proposicao": 17,
      "nome_interesse": "Direitos Humanos",
      "descricao_interesse": "."
    }
  },
  {
    "model": "api.interesse",
    "pk": 18,
    "fields": {
      "id_leggo": "7c4cbac341769f758f433b3f2e0c08c9",
      "interesse": "direitos-humanos",
      "apelido": "Armamento",
      "tema": "Armamento;Segurança pública",
      "tema_slug": "armamento;seguranca-publica",
      "keywords": "nan",
      "advocacy_link": "nan",
      "tipo_agenda": "nan",
      "proposicao": 18,
      "nome_interesse": "Direitos Humanos",
      "descricao_interesse": "."
    }
  },
  {
    "model": "api.interesse",
    "pk": 19,
    "fields": {
      "id_leggo": "7ce128eb8c9102201fdd73710dcd3b29",
      "interesse": "direitos-humanos",
      "apelido": "Prazo de internação no sistema socioeducativo",
      "tema": "Socioeducativo;ECA",
      "tema_slug": "socioeducativo;eca",
      "keywords": "nan",
      "advocacy_link": "nan",
      "tipo_agenda": "nan",
      "proposicao": 19,
      "nome_interesse": "Direitos Humanos",
      "descricao_interesse": "."
    }
  },
  {
    "model": "api.interesse",
    "pk": 20,
    "fields": {
      "id_leggo": "7ec45d1ae9644480113182740eea283b",
      "interesse": "direitos-humanos",
      "apelido": "Licenciamento compulsório de medicamentos",
      "tema": "Licenciamento compulsório;Medicamentos;Vacinas",
      "tema_slug": "licenciamento-compulsorio;medicamentos;vacinas",
      "keywords": "nan",
      "advocacy_link": "nan",
      "tipo_agenda": "nan",
      "proposicao": 20,
      "nome_interesse": "Direitos Humanos",
      "descricao_interesse": "."
    }
  },
  {
    "model": "api.interesse",
    "pk": 21,
    "fields": {
      "id_leggo": "8146c938a148a04cf2a216d4f2461258",
      "interesse": "direitos-humanos",
      "apelido": "Cannabis medicinal",
      "tema": "Segurança pública;Cannabis",
      "tema_slug": "seguranca-publica;cannabis",
      "keywords": "nan",
      "advocacy_link": "nan",
      "tipo_agenda": "nan",
      "proposicao": 21,
      "nome_interesse": "Direitos Humanos",
      "descricao_interesse": "."
    }
  },
  {
    "model": "api.interesse",
    "pk": 22,
    "fields": {
      "id_leggo": "887932a31c7b3eb0ab0c414ca3d51457",
      "interesse": "direitos-humanos",
      "apelido": "Prevenção ao uso de álcool, tabaco e outras drogas nas escolas",
      "tema": "Segurança pública;Educação;Drogas",
      "tema_slug": "seguranca-publica;educacao;drogas",
      "keywords": "nan",
      "advocacy_link": "nan",
      "tipo_agenda": "nan",
      "proposicao": 22,
      "nome_interesse": "Direitos Humanos",
      "descricao_interesse": "."
    }
  },
  {
    "model": "api.interesse",
    "pk": 23,
    "fields": {
      "id_leggo": "8d974ba88f593b800d77db6dc6f1f0f1",
      "interesse": "direitos-humanos",
      "apelido": "Trabalho a partir dos 14 anos",
      "tema": "Trabalho infantil",
      "tema_slug": "trabalho-infantil",
      "keywords": "nan",
      "advocacy_link": "nan",
      "tipo_agenda": "nan",
      "proposicao": 23,
      "nome_interesse": "Direitos Humanos",
      "descricao_interesse": "."
    }
  },
  {
    "model": "api.interesse",
    "pk": 24,
    "fields": {
      "id_leggo": "917ddf07f9a4350fad09d6f063f787af",
      "interesse": "direitos-humanos",
      "apelido": "Trabalho escravo como crime hediondo",
      "tema": "Trabalho escravo;Crimes hediondos",
      "tema_slug": "trabalho-escravo;crimes-hediondos",
      "keywords": "nan",
      "advocacy_link": "nan",
      "tipo_agenda": "nan",
      "proposicao": 24,
      "nome_interesse": "Direitos Humanos",
      "descricao_interesse": "."
    }
  },
  {
    "model": "api.interesse",
    "pk": 25,
    "fields": {
      "id_leggo": "9cc39bc2b73e450095983bfd19d7647a",
      "interesse": "direitos-humanos",
      "apelido": "Ensino domiciliar",
      "tema": "Educação;Ensino domiciliar",
      "tema_slug": "educacao;ensino-domiciliar",
      "keywords": "nan",
      "advocacy_link": "nan",
      "tipo_agenda": "nan",
      "proposicao": 25,
      "nome_interesse": "Direitos Humanos",
      "descricao_interesse": "."
    }
  },
  {
    "model": "api.interesse",
    "pk": 26,
    "fields": {
      "id_leggo": "a8d684b8ff8f9ccd07710478259ae3c3",
      "interesse": "direitos-humanos",
      "apelido": "Trabalho escravo",
      "tema": "Trabalho escravo",
      "tema_slug": "trabalho-escravo",
      "keywords": "nan",
      "advocacy_link": "nan",
      "tipo_agenda": "nan",
      "proposicao": 26,
      "nome_interesse": "Direitos Humanos",
      "descricao_interesse": "."
    }
  },
  {
    "model": "api.interesse",
    "pk": 27,
    "fields": {
      "id_leggo": "c64582a6f372d95e90ec91b54d9b9658",
      "interesse": "direitos-humanos",
      "apelido": "Prazo de internação no sistema socioeducativo",
      "tema": "Socioeducativo;ECA",
      "tema_slug": "socioeducativo;eca",
      "keywords": "nan",
      "advocacy_link": "nan",
      "tipo_agenda": "nan",
      "proposicao": 27,
      "nome_interesse": "Direitos Humanos",
      "descricao_interesse": "."
    }
  },
  {
    "model": "api.interesse",
    "pk": 28,
    "fields": {
      "id_leggo": "c910975e8226ab40cdfa724f4b920fec",
      "interesse": "direitos-humanos",
      "apelido": "Lei Antidrogas",
      "tema": "Direito Penal;Drogas;Segurança pública",
      "tema_slug": "direito-penal;drogas;seguranca-publica",
      "keywords": "nan",
      "advocacy_link": "nan",
      "tipo_agenda": "nan",
      "proposicao": 28,
      "nome_interesse": "Direitos Humanos",
      "descricao_interesse": "."
    }
  },
  {
    "model": "api.interesse",
    "pk": 29,
    "fields": {
      "id_leggo": "d377fbe7ebeff34b20abebe245cc1b02",
      "interesse": "direitos-humanos",
      "apelido": "Ensino domiciliar",
      "tema": "Educação;Ensino domiciliar;Abandono intelectual",
      "tema_slug": "educacao;ensino-domiciliar;abandono-intelectual",
      "keywords": "nan",
      "advocacy_link": "nan",
      "tipo_agenda": "nan",
      "proposicao": 29,
      "nome_interesse": "Direitos Humanos",
      "descricao_interesse": "."
    }
  },
  {
    "model": "api.interesse",
    "pk": 30,
    "fields": {
      "id_leggo": "d6bea11bba17f549660904a4bc7e669f",
      "interesse": "direitos-humanos",
      "apelido": "Redução da maioridade penal",
      "tema": "Segurança pública;Maioridade penal",
      "tema_slug": "seguranca-publica;maioridade-penal",
      "keywords": "nan",
      "advocacy_link": "nan",
      "tipo_agenda": "nan",
      "proposicao": 30,
      "nome_interesse": "Direitos Humanos",
      "descricao_interesse": "."
    }
  },
  {
    "model": "api.interesse",
    "pk": 31,
    "fields": {
      "id_leggo": "d9f8204212bfa76133e73018379feee9",
      "interesse": "direitos-humanos",
      "apelido": "Trabalho infantil artístico",
      "tema": "Trabalho infantil",
      "tema_slug": "trabalho-infantil",
      "keywords": "nan",
      "advocacy_link": "nan",
      "tipo_agenda": "nan",
      "proposicao": 31,
      "nome_interesse": "Direitos Humanos",
      "descricao_interesse": "."
    }
  },
  {
    "model": "api.interesse",
    "pk": 32,
    "fields": {
      "id_leggo": "e011b9f17f6e2b01801272d6482401ed",
      "interesse": "direitos-humanos",
      "apelido": "Revoga a Lei de Segurança Nacional",
      "tema": "Estado Democrático de Direito;Segurança Nacional;Direito Penal",
      "tema_slug": "estado-democratico-de-direito;seguranca-nacional;direito-penal",
      "keywords": "nan",
      "advocacy_link": "nan",
      "tipo_agenda": "nan",
      "proposicao": 32,
      "nome_interesse": "Direitos Humanos",
      "descricao_interesse": "."
    }
  },
  {
    "model": "api.interesse",
    "pk": 33,
    "fields": {
      "id_leggo": "e7338f9d01d0925a813001efa14dcb3b",
      "interesse": "direitos-humanos",
      "apelido": "Dispõe sobre Orçamentos Temáticos",
      "tema": "Orçamento;Minorias",
      "tema_slug": "orcamento;minorias",
      "keywords": "nan",
      "advocacy_link": "nan",
      "tipo_agenda": "nan",
      "proposicao": 33,
      "nome_interesse": "Direitos Humanos",
      "descricao_interesse": "."
    }
  },
  {
    "model": "api.interesse",
    "pk": 34,
    "fields": {
      "id_leggo": "ebfdc89f91ebd5eac5fdc06100cce4af",
      "interesse": "direitos-humanos",
      "apelido": "Altera as cotas nas universidades e instituições federais de ensino técnico de nível médio federais",
      "tema": "Educação;Ações afirmativas;Cotas",
      "tema_slug": "educacao;acoes-afirmativas;cotas",
      "keywords": "nan",
      "advocacy_link": "nan",
      "tipo_agenda": "nan",
      "proposicao": 34,
      "nome_interesse": "Direitos Humanos",
      "descricao_interesse": "."
    }
  },
  {
    "model": "api.interesse",
    "pk": 35,
    "fields": {
      "id_leggo": "f273c0a8857e1fa869068152a77217b5",
      "interesse": "direitos-humanos",
      "apelido": "Abuso de autoridade fundado em preconceito",
      "tema": "Abuso de autoridade;Discriminação;Racismo",
      "tema_slug": "abuso-de-autoridade;discriminacao;racismo",
      "keywords": "nan",
      "advocacy_link": "nan",
      "tipo_agenda": "nan",
      "proposicao": 35,
      "nome_interesse": "Direitos Humanos",
      "descricao_interesse": "."
    }
  },
  {
    "model": "api.interesse",
    "pk": 36,
    "fields": {
      "id_leggo": "fa97e75f189ec99d4f19f4726beeead6",
      "interesse": "direitos-humanos",
      "apelido": "Revoga a Lei de Segurança Nacional",
      "tema": "Estado Democrático de Direito;Segurança Nacional;Direito Penal",
      "tema_slug": "estado-democratico-de-direito;seguranca-nacional;direito-penal",
      "keywords": "nan",
      "advocacy_link": "nan",
      "tipo_agenda": "nan",
      "proposicao": 36,
      "nome_interesse": "Direitos Humanos",
      "descricao_interesse": "."
    }
  }
]
